access_spotify/__init__.py
access_spotify/get_album_art.py
access_spotify/get_album_data.py
access_spotify/get_album_details.py
access_spotify/get_all_album_art.py
access_spotify/get_all_album_data.py
access_spotify/get_spotify_access.py
access_spotify/run_all.py
access_spotify/spotify_credentials.py
access_spotify-1.1.data/scripts/access_script.py
access_spotify-1.1.dist-info/LICENSE
access_spotify-1.1.dist-info/METADATA
access_spotify-1.1.dist-info/WHEEL
access_spotify-1.1.dist-info/top_level.txt
access_spotify-1.1.dist-info/RECORD
